loggage/__init__.py
loggage/core/__init__.py
loggage/core/context.py
loggage/core/decorators.py
loggage/core/exceptions.py
loggage/core/hybrid_logger.py
loggage/core/logger.py
loggage/core/models.py
loggage/core/queue.py
loggage/core/adapters/__init__.py
loggage/core/adapters/bottle_adapter.py
loggage/core/handlers/__init__.py
loggage/core/handlers/base.py
loggage/core/handlers/elasticsearch.py
loggage/core/handlers/factory.py
loggage/core/handlers/mysql.py
loggage/core/handlers/redis.py
loggage/example/__init__.py
loggage/example/bottle_example.py
loggage/example/fastapi_example.py
loggage/example/main.py
loggage/utils/__init__.py
loggage/utils/config.py
loggage/utils/tools.py
loggage-0.8.0.dist-info/licenses/LICENSE
loggage-0.8.0.dist-info/METADATA
loggage-0.8.0.dist-info/WHEEL
loggage-0.8.0.dist-info/top_level.txt
loggage-0.8.0.dist-info/RECORD
