Metadata-Version: 2.4
Name: loggage
Version: 0.8.0
Summary: Store you operation log to different backend.
Classifier: Development Status :: 4 - Beta
Classifier: Intended Audience :: Developers
Classifier: Programming Language :: Python :: 3
Classifier: Programming Language :: Python :: 3.9
Classifier: Programming Language :: Python :: 3.10
Classifier: Programming Language :: Python :: 3.11
Classifier: Programming Language :: Python :: 3.12
Requires-Python: >=3.9
License-File: LICENSE
Requires-Dist: aiomysql>=0.2.0
Requires-Dist: elasticsearch[async]==7.17
Requires-Dist: pydantic>=2.10.6
Requires-Dist: pymysql>=1.1.1
Requires-Dist: pyyaml>=6.0.2
Dynamic: license-file
